CONTRIBUTING.md
MANIFEST.in
README.rst
setup.py
docs/HISTORY.txt
docs/LICENSE.GPL
docs/LICENSE.txt
eea/__init__.py
eea.api.versions.egg-info/PKG-INFO
eea.api.versions.egg-info/SOURCES.txt
eea.api.versions.egg-info/dependency_links.txt
eea.api.versions.egg-info/entry_points.txt
eea.api.versions.egg-info/namespace_packages.txt
eea.api.versions.egg-info/not-zip-safe
eea.api.versions.egg-info/requires.txt
eea.api.versions.egg-info/top_level.txt
eea/api/__init__.py
eea/api/versions/README.txt
eea/api/versions/__init__.py
eea/api/versions/configure.zcml
eea/api/versions/interfaces.py
eea/api/versions/profiles.zcml
eea/api/versions/setuphandlers.py
eea/api/versions/version.txt
eea/api/versions/browser/__init__.py
eea/api/versions/browser/configure.zcml
eea/api/versions/browser/relations.py
eea/api/versions/locales/__init__.py
eea/api/versions/locales/eea.pot
eea/api/versions/locales/plone-manual.pot
eea/api/versions/locales/update.sh
eea/api/versions/locales/bg/LC_MESSAGES/eea.po
eea/api/versions/locales/bg/LC_MESSAGES/plone.po
eea/api/versions/locales/cs/LC_MESSAGES/eea.po
eea/api/versions/locales/cs/LC_MESSAGES/plone.po
eea/api/versions/locales/da/LC_MESSAGES/eea.po
eea/api/versions/locales/da/LC_MESSAGES/plone.po
eea/api/versions/locales/de/LC_MESSAGES/eea.po
eea/api/versions/locales/de/LC_MESSAGES/plone.po
eea/api/versions/locales/el/LC_MESSAGES/eea.po
eea/api/versions/locales/el/LC_MESSAGES/plone.po
eea/api/versions/locales/en/LC_MESSAGES/eea.po
eea/api/versions/locales/en/LC_MESSAGES/plone.po
eea/api/versions/locales/es/LC_MESSAGES/eea.po
eea/api/versions/locales/es/LC_MESSAGES/plone.po
eea/api/versions/locales/et/LC_MESSAGES/eea.po
eea/api/versions/locales/et/LC_MESSAGES/plone.po
eea/api/versions/locales/eu/LC_MESSAGES/eea.po
eea/api/versions/locales/eu/LC_MESSAGES/plone.po
eea/api/versions/locales/fi/LC_MESSAGES/eea.po
eea/api/versions/locales/fi/LC_MESSAGES/plone.po
eea/api/versions/locales/fr/LC_MESSAGES/eea.po
eea/api/versions/locales/fr/LC_MESSAGES/plone.po
eea/api/versions/locales/hr/LC_MESSAGES/eea.po
eea/api/versions/locales/hr/LC_MESSAGES/plone.po
eea/api/versions/locales/hu/LC_MESSAGES/eea.po
eea/api/versions/locales/hu/LC_MESSAGES/plone.po
eea/api/versions/locales/is/LC_MESSAGES/eea.po
eea/api/versions/locales/is/LC_MESSAGES/plone.po
